appworld/.source/apps.bundle
appworld/.source/tests.bundle
appworld/__init__.py
appworld/api_docs.py
appworld/apps/__init__.py
appworld/apps/api_lib.py
appworld/apps/factory_lib.py
appworld/apps/model_lib.py
appworld/apps/response_lib.py
appworld/cli.py
appworld/collections/api_docs.py
appworld/collections/api_docs.pyi
appworld/collections/apis.py
appworld/collections/apis.pyi
appworld/collections/models.py
appworld/collections/models.pyi
appworld/common/__init__.py
appworld/common/code_parsing.py
appworld/common/constants.py
appworld/common/copy.py
appworld/common/datetime.py
appworld/common/path_store.py
appworld/common/random.py
appworld/common/safety_guard.py
appworld/common/types.py
appworld/common/utils.py
appworld/download.py
appworld/environment.py
appworld/evaluator.py
appworld/ground_truth.py
appworld/install.py
appworld/leaderboard.py
appworld/requester.py
appworld/serve/apis.py
appworld/serve/environment.py
appworld/serve/playground.html
appworld/serve/static/icon.png
appworld/task.py
appworld/verify.py
appworld-0.1.3.dist-info/LICENSE
appworld-0.1.3.dist-info/METADATA
appworld-0.1.3.dist-info/WHEEL
appworld-0.1.3.dist-info/entry_points.txt
appworld-0.1.3.dist-info/RECORD
